klaatu_python/__init__.py
klaatu_python/case.py
klaatu_python/lock.py
klaatu_python/utils.py
klaatu_python-2.3.0.dist-info/licenses/LICENSE
klaatu_python-2.3.0.dist-info/METADATA
klaatu_python-2.3.0.dist-info/WHEEL
klaatu_python-2.3.0.dist-info/top_level.txt
klaatu_python-2.3.0.dist-info/RECORD
