Metadata-Version: 2.4
Name: klaatu-python
Version: 2.3.0
Author-email: Robert Huselius <robert@huseli.us>
License-Expression: GPL-3.0-only
Project-URL: Homepage, https://github.com/Eboreg/klaatu-python
Project-URL: Issues, https://github.com/Eboreg/klaatu-python/issues
Project-URL: Source, https://github.com/Eboreg/klaatu-python
Requires-Python: >=3.7
License-File: LICENSE
Provides-Extra: dev
Requires-Dist: ipython; extra == "dev"
Requires-Dist: ipdb; extra == "dev"
Requires-Dist: isort; extra == "dev"
Requires-Dist: pylint; extra == "dev"
Dynamic: license-file
